MANIFEST.in
README.rst
VERSION
requirements.txt
setup.py
ansible_netbox_inventory.egg-info/PKG-INFO
ansible_netbox_inventory.egg-info/SOURCES.txt
ansible_netbox_inventory.egg-info/dependency_links.txt
ansible_netbox_inventory.egg-info/requires.txt
ansible_netbox_inventory.egg-info/top_level.txt
netbox/__init__.py
netbox/netbox.py
netbox/netbox.yml
tests/__init__.py
tests/__init__.pyc
tests/requirements.txt
tests/test_netbox.py
tests/test_netbox.pyc
tests/__pycache__/__init__.cpython-35.pyc
tests/__pycache__/test_netbox.cpython-27-PYTEST.pyc
tests/__pycache__/test_netbox.cpython-35-PYTEST.pyc