Metadata-Version: 1.1
Name: ansible-netbox-inventory
Version: 1.0.9
Summary: Ansible dynamic inventory script for Netbox
Home-page: https://github.com/AAbouZaid/netbox-as-ansible-inventory
Author: Ahmed AbouZaid
Author-email: ahmed.m@aabouzaid.com
License: GPLv3
Keywords: ansible,netbox,dynamic,inventory
Platform: UNKNOWN
Classifier: Environment :: Console
Classifier: Intended Audience :: Developers
Classifier: Intended Audience :: System Administrators
Classifier: Topic :: Utilities
Classifier: Topic :: System :: Installation/Setup
Classifier: Topic :: System :: Systems Administration
Classifier: Development Status :: 5 - Production/Stable
Classifier: Programming Language :: Python :: 2
Classifier: Programming Language :: Python :: 2.6
Classifier: Programming Language :: Python :: 2.7
Classifier: Programming Language :: Python :: 3
Classifier: Programming Language :: Python :: 3.5
Classifier: License :: OSI Approved :: GNU General Public License v3 or later (GPLv3+)
